vipes/__init__.py
vipes/cli.py
vipes/interpreter.py
vipes-0.0.5.dist-info/LICENSE
vipes-0.0.5.dist-info/METADATA
vipes-0.0.5.dist-info/WHEEL
vipes-0.0.5.dist-info/entry_points.txt
vipes-0.0.5.dist-info/top_level.txt
vipes-0.0.5.dist-info/RECORD
