Metadata-Version: 2.1
Name: vipes
Version: 0.0.5
Summary: The most reliable script manager for crossplatform projects
Home-page: https://github.com/flobbun/vipes
Author: Jhon
Keywords: script,manager,crossplatform,configuration
Classifier: Programming Language :: Python :: 3.7
Classifier: Operating System :: OS Independent
Requires-Python: >=3.7
License-File: LICENSE
